autogen_xai_client/__init__.py
autogen_xai_client/_model_info.py
autogen_xai_client/_openai_client.py
autogen_xai_client/_xai_client.py
autogen_xai_client/config/__init__.py
autogen_xai_client-0.1.1.dist-info/METADATA
autogen_xai_client-0.1.1.dist-info/WHEEL
autogen_xai_client-0.1.1.dist-info/RECORD
