Metadata-Version: 2.1
Name: autogen-xai-client
Version: 0.1.1
Summary: 
Author: me020523
Author-email: me020523@gmail.com
Requires-Python: >=3.10,<4.0
Classifier: Programming Language :: Python :: 3
Classifier: Programming Language :: Python :: 3.10
Classifier: Programming Language :: Python :: 3.11
Classifier: Programming Language :: Python :: 3.12
Requires-Dist: autogen-core (>=0.4.0.dev8,<0.5.0)
